pyqt_modern_slider/__init__.py
pyqt_modern_slider/modernSlider.py
pyqt_modern_slider-0.0.5.dist-info/LICENSE
pyqt_modern_slider-0.0.5.dist-info/METADATA
pyqt_modern_slider-0.0.5.dist-info/WHEEL
pyqt_modern_slider-0.0.5.dist-info/top_level.txt
pyqt_modern_slider-0.0.5.dist-info/RECORD
