Metadata-Version: 2.1
Name: pyqt-modern-slider
Version: 0.0.5
Summary: PyQt modern styled slider
Home-page: https://github.com/yjg30737/pyqt-modern-slider.git
Author: Jung Gyu Yoon
Author-email: yjg30737@gmail.com
License: MIT
License-File: LICENSE
Requires-Dist: PyQt5 (>=5.8)
